[
	{
		"title": "Year Progress",
		"info": "Check How much year has been progressed",
		"appRoute": "/year-progress"
	},
	{
		"title": "Base Convertor",
		"info": "Convert a Number to Any Base",
		"appRoute": "/base-convertor"
	},
	{
		"title": "Investment Calculator",
		"info": "Calculate Your Investment",
		"appRoute": "/investment-calculator"
	},
	{
		"title": "Temperature Convertor",
		"info": "Convert Temperature between kelvin celcius and farenheit",
		"appRoute": "/temperature-convertor"
	}
]
